{
    "pipes": [],
    "interfaces": [
        {
            "name": "User",
            "id": "interface-User-9c7e5f1bbbab702cb032307d130876cb68969b0cd4eedef32a0c8cad8081a54e5f8f577ed6ad4539c1b99a1d246cb34031d198c2ea8eba440e64e91b14f01fdc",
            "file": "projects/component-lib/src/lib/stories/User.ts",
            "deprecated": false,
            "deprecationMessage": "",
            "type": "interface",
            "sourceCode": "export interface User {}\n",
            "properties": [],
            "indexSignatures": [],
            "methods": []
        }
    ],
    "injectables": [],
    "guards": [],
    "interceptors": [],
    "classes": [],
    "directives": [],
    "components": [
        {
            "name": "AppComponent",
            "id": "component-AppComponent-af1412002a029bfa131751f8b821ad43fe8cee0e7230d2bd55358af5fa71a223e19464178ee4bf5392bd9e14d9fb85a7a4defc4a2092380c306e06a7925fdda6",
            "file": "src/app/app.component.ts",
            "encapsulation": [],
            "entryComponents": [],
            "inputs": [],
            "outputs": [],
            "providers": [],
            "selector": "comp-lib",
            "styleUrls": [
                "./app.component.scss"
            ],
            "styles": [],
            "templateUrl": [
                "./app.component.html"
            ],
            "viewProviders": [],
            "inputsClass": [],
            "outputsClass": [],
            "propertiesClass": [
                {
                    "name": "title",
                    "defaultValue": "'mf-component-library'",
                    "deprecated": false,
                    "deprecationMessage": "",
                    "type": "string",
                    "optional": false,
                    "description": "",
                    "line": 9
                }
            ],
            "methodsClass": [],
            "deprecated": false,
            "deprecationMessage": "",
            "hostBindings": [],
            "hostListeners": [],
            "description": "",
            "rawdescription": "\n",
            "type": "component",
            "sourceCode": "import { Component } from '@angular/core';\n\n@Component({\n  selector: 'comp-lib',\n  templateUrl: './app.component.html',\n  styleUrls: ['./app.component.scss']\n})\nexport class AppComponent {\n  title = 'mf-component-library';\n}\n",
            "assetsDirs": [],
            "styleUrlsData": [
                {
                    "data": "mat-button-toggle-group {\n  margin-left: 12px;\n}\n",
                    "styleUrl": "./app.component.scss"
                }
            ],
            "stylesData": "",
            "templateData": "hello ffrommnew omponent library\n\n<mat-card>Simple card</mat-card>\n<mat-button-toggle-group name=\"fontStyle\" aria-label=\"Font Style\">\n    <mat-button-toggle value=\"bold\">Bold</mat-button-toggle>\n    <mat-button-toggle value=\"italic\">Italic</mat-button-toggle>\n    <mat-button-toggle value=\"underline\">Underline</mat-button-toggle>\n  </mat-button-toggle-group>\n\n"
        },
        {
            "name": "ButtonComponentComponent",
            "id": "component-ButtonComponentComponent-1bb49737acc4d048cf24de7336dc3f6f7a0f465a1bfdc3f87c4cfaccdf326a0088016615785bcee9113662f907a81d511b1f50b61b3824fac2d96977c89f76aa",
            "file": "projects/component-lib/src/lib/stories/components/button-component/button-component.component.ts",
            "encapsulation": [],
            "entryComponents": [],
            "inputs": [],
            "outputs": [],
            "providers": [],
            "selector": "lib-button-component",
            "styleUrls": [
                "./button-component.component.css"
            ],
            "styles": [],
            "templateUrl": [
                "./button-component.component.html"
            ],
            "viewProviders": [],
            "inputsClass": [
                {
                    "name": "text",
                    "defaultValue": "'Click me!'",
                    "deprecated": false,
                    "deprecationMessage": "",
                    "line": 9,
                    "type": "string",
                    "decorators": []
                }
            ],
            "outputsClass": [],
            "propertiesClass": [],
            "methodsClass": [
                {
                    "name": "ngOnInit",
                    "args": [],
                    "optional": false,
                    "returnType": "void",
                    "typeParameters": [],
                    "line": 12,
                    "deprecated": false,
                    "deprecationMessage": ""
                }
            ],
            "deprecated": false,
            "deprecationMessage": "",
            "hostBindings": [],
            "hostListeners": [],
            "description": "",
            "rawdescription": "\n",
            "type": "component",
            "sourceCode": "import { Component, Input, OnInit } from '@angular/core';\n\n@Component({\n  selector: 'lib-button-component',\n  templateUrl: './button-component.component.html',\n  styleUrls: ['./button-component.component.css']\n})\nexport class ButtonComponentComponent implements OnInit {\n  @Input() text: string= 'Click me!';\n  constructor() { }\n\n  ngOnInit(): void {\n  }\n\n}\n",
            "assetsDirs": [],
            "styleUrlsData": [
                {
                    "data": "",
                    "styleUrl": "./button-component.component.css"
                }
            ],
            "stylesData": "",
            "constructorObj": {
                "name": "constructor",
                "description": "",
                "deprecated": false,
                "deprecationMessage": "",
                "args": [],
                "line": 9
            },
            "implements": [
                "OnInit"
            ],
            "templateData": "<button >{{text}}</button>"
        },
        {
            "name": "CustomCompComponent",
            "id": "component-CustomCompComponent-6be07f0ab32e3e4e06eb3c90dbbd82529027a5473587873882d8fe6d1bcbe5b19555daace0ed12fbe564d04fa3698a3f3de5844be5109e5bd0095181285b65d3",
            "file": "projects/component-lib/src/lib/stories/components/custom-comp/custom-comp.component.ts",
            "encapsulation": [],
            "entryComponents": [],
            "inputs": [],
            "outputs": [],
            "providers": [],
            "selector": "lib-custom-comp",
            "styleUrls": [
                "./custom-comp.component.css"
            ],
            "styles": [],
            "templateUrl": [
                "./custom-comp.component.html"
            ],
            "viewProviders": [],
            "inputsClass": [],
            "outputsClass": [],
            "propertiesClass": [],
            "methodsClass": [
                {
                    "name": "ngOnInit",
                    "args": [],
                    "optional": false,
                    "returnType": "void",
                    "typeParameters": [],
                    "line": 12,
                    "deprecated": false,
                    "deprecationMessage": ""
                }
            ],
            "deprecated": false,
            "deprecationMessage": "",
            "hostBindings": [],
            "hostListeners": [],
            "description": "",
            "rawdescription": "\n",
            "type": "component",
            "sourceCode": "import { Component, OnInit } from '@angular/core';\n\n@Component({\n  selector: 'lib-custom-comp',\n  templateUrl: './custom-comp.component.html',\n  styleUrls: ['./custom-comp.component.css']\n})\nexport class CustomCompComponent implements OnInit {\n\n  constructor() { }\n\n  ngOnInit(): void {\n  }\n\n}\n",
            "assetsDirs": [],
            "styleUrlsData": [
                {
                    "data": "",
                    "styleUrl": "./custom-comp.component.css"
                }
            ],
            "stylesData": "",
            "constructorObj": {
                "name": "constructor",
                "description": "",
                "deprecated": false,
                "deprecationMessage": "",
                "args": [],
                "line": 8
            },
            "implements": [
                "OnInit"
            ],
            "templateData": "<div>\n    this will be a card\n</div>"
        },
        {
            "name": "EmptyRouteComponent",
            "id": "component-EmptyRouteComponent-ac1c0c3e0464b5bf1187acbfef890ed4a0da1ca7d43f328ba66ec12687da1a45fe509f029b20d200dacef5e83dbe99283fe5fb7d108ad96791164420c9c27213",
            "file": "src/app/empty-route/empty-route.component.ts",
            "encapsulation": [],
            "entryComponents": [],
            "inputs": [],
            "outputs": [],
            "providers": [],
            "selector": "app-empty-route",
            "styleUrls": [],
            "styles": [],
            "template": "",
            "templateUrl": [],
            "viewProviders": [],
            "inputsClass": [],
            "outputsClass": [],
            "propertiesClass": [],
            "methodsClass": [],
            "deprecated": false,
            "deprecationMessage": "",
            "hostBindings": [],
            "hostListeners": [],
            "description": "",
            "rawdescription": "\n",
            "type": "component",
            "sourceCode": "import { Component } from '@angular/core';\n\n@Component({\n  selector: 'app-empty-route',\n  template: '',\n})\nexport class EmptyRouteComponent {}\n",
            "assetsDirs": [],
            "styleUrlsData": "",
            "stylesData": ""
        },
        {
            "name": "InputComponent",
            "id": "component-InputComponent-a55fc4964291dba25d8f3c39edd8f248963671d336c07603b84d4f906ef281748f77964e31784c4dc939a5d0d5ea9dde7491f23032b4a019f78f6320991ebca3",
            "file": "projects/component-lib/src/lib/stories/components/input/input.component.ts",
            "encapsulation": [],
            "entryComponents": [],
            "inputs": [],
            "outputs": [],
            "providers": [],
            "selector": "lib-input",
            "styleUrls": [
                "./input.component.css"
            ],
            "styles": [],
            "templateUrl": [
                "./input.component.html"
            ],
            "viewProviders": [],
            "inputsClass": [],
            "outputsClass": [],
            "propertiesClass": [],
            "methodsClass": [
                {
                    "name": "ngOnInit",
                    "args": [],
                    "optional": false,
                    "returnType": "void",
                    "typeParameters": [],
                    "line": 12,
                    "deprecated": false,
                    "deprecationMessage": ""
                }
            ],
            "deprecated": false,
            "deprecationMessage": "",
            "hostBindings": [],
            "hostListeners": [],
            "description": "",
            "rawdescription": "\n",
            "type": "component",
            "sourceCode": "import { Component, OnInit } from '@angular/core';\n\n@Component({\n  selector: 'lib-input',\n  templateUrl: './input.component.html',\n  styleUrls: ['./input.component.css']\n})\nexport class InputComponent implements OnInit {\n\n  constructor() { }\n\n  ngOnInit(): void {\n  }\n\n}\n",
            "assetsDirs": [],
            "styleUrlsData": [
                {
                    "data": "",
                    "styleUrl": "./input.component.css"
                }
            ],
            "stylesData": "",
            "constructorObj": {
                "name": "constructor",
                "description": "",
                "deprecated": false,
                "deprecationMessage": "",
                "args": [],
                "line": 8
            },
            "implements": [
                "OnInit"
            ],
            "templateData": "<div>\n    <label for=\"name\">\n        Insert value: <input />\n    </label>\n</div>\n"
        },
        {
            "name": "NavbarComponent",
            "id": "component-NavbarComponent-92889ac725c129fe57e2aafa7af4b5f7ad54d281621a70bb0521fb106bf6fed96400e107dce9a2ce1fd36933f27e6483928bd35a0c8afd7ec910be7efc461bb7",
            "file": "projects/component-lib/src/lib/stories/components/navbar/navbar.component.ts",
            "encapsulation": [],
            "entryComponents": [],
            "inputs": [],
            "outputs": [],
            "providers": [],
            "selector": "lib-navbar",
            "styleUrls": [
                "./navbar.component.css"
            ],
            "styles": [],
            "templateUrl": [
                "./navbar.component.html"
            ],
            "viewProviders": [],
            "inputsClass": [],
            "outputsClass": [],
            "propertiesClass": [],
            "methodsClass": [
                {
                    "name": "ngOnInit",
                    "args": [],
                    "optional": false,
                    "returnType": "void",
                    "typeParameters": [],
                    "line": 13,
                    "deprecated": false,
                    "deprecationMessage": ""
                }
            ],
            "deprecated": false,
            "deprecationMessage": "",
            "hostBindings": [],
            "hostListeners": [],
            "description": "",
            "rawdescription": "\n",
            "type": "component",
            "sourceCode": "import { Component, OnInit } from '@angular/core';\n\n@Component({\n  selector: 'lib-navbar',\n  templateUrl: './navbar.component.html',\n  styleUrls: ['./navbar.component.css']\n})\nexport class NavbarComponent implements OnInit {\n\n  constructor() { \n  }\n\n  ngOnInit(): void {\n  }\n\n}\n",
            "assetsDirs": [],
            "styleUrlsData": [
                {
                    "data": "",
                    "styleUrl": "./navbar.component.css"
                }
            ],
            "stylesData": "",
            "constructorObj": {
                "name": "constructor",
                "description": "",
                "deprecated": false,
                "deprecationMessage": "",
                "args": [],
                "line": 8
            },
            "implements": [
                "OnInit"
            ],
            "templateData": "<mat-button-toggle-group name=\"fontStyle\" aria-label=\"Font Style\">\n    <mat-button-toggle value=\"bold\">Bold</mat-button-toggle>\n    <mat-button-toggle value=\"italic\">Italic</mat-button-toggle>\n    <mat-button-toggle value=\"underline\">Underline</mat-button-toggle>\n  </mat-button-toggle-group>\n"
        }
    ],
    "modules": [
        {
            "name": "AppModule",
            "id": "module-AppModule-c144ee48d31831524bdcffb11b077b547a163d060ffa06f97251b163307dfa7d18f3d8ca7e0ecdd7084851e27592ec8f217a9bab47808ccd5fd865ab8294eb3d",
            "description": "",
            "deprecationMessage": "",
            "deprecated": false,
            "file": "src/app/app.module.ts",
            "methods": [],
            "sourceCode": "import { NgModule } from '@angular/core';\nimport { BrowserModule } from '@angular/platform-browser';\nimport { MatSliderModule } from '@angular/material/slider';\nimport {MatCardModule} from '@angular/material/card';\nimport {MatButtonToggleModule} from '@angular/material/button-toggle';\n\n\nimport { AppComponent } from './app.component';\n\n@NgModule({\n  declarations: [\n    AppComponent\n  ],\n  imports: [\n    BrowserModule,\n    MatSliderModule,\n    MatCardModule,\n    MatButtonToggleModule\n  ],\n  providers: [],\n  bootstrap: [AppComponent]\n})\nexport class AppModule { }\n",
            "children": [
                {
                    "type": "providers",
                    "elements": []
                },
                {
                    "type": "declarations",
                    "elements": [
                        {
                            "name": "AppComponent"
                        }
                    ]
                },
                {
                    "type": "imports",
                    "elements": []
                },
                {
                    "type": "exports",
                    "elements": []
                },
                {
                    "type": "bootstrap",
                    "elements": [
                        {
                            "name": "AppComponent"
                        }
                    ]
                },
                {
                    "type": "classes",
                    "elements": []
                }
            ]
        },
        {
            "name": "UiComponentsModule",
            "id": "module-UiComponentsModule-b2acb129a0e90bbfe367e624b744b1f8f498c95976e790cf311e56faad3ce83b0f74b46241f3a226f1fa8507b41d96c56979e6234ef233d8c691f548419c93b0",
            "description": "",
            "deprecationMessage": "",
            "deprecated": false,
            "file": "projects/component-lib/src/lib/ui-components.module.ts",
            "methods": [],
            "sourceCode": "import { NgModule } from '@angular/core';\nimport { ButtonComponentComponent } from './stories/components/button-component/button-component.component';\nimport { InputComponent } from './stories/components/input/input.component';\nimport { CustomCompComponent } from './stories/components/custom-comp/custom-comp.component';\nimport { NavbarComponent } from './stories/components/navbar/navbar.component';\nimport { MatSliderModule } from '@angular/material/slider';\nimport {MatButtonToggleModule} from '@angular/material/button-toggle';\n\n\n@NgModule({\n  declarations: [\n    ButtonComponentComponent,\n    InputComponent,\n    CustomCompComponent,\n    NavbarComponent\n  ],\n  exports: [\n    ButtonComponentComponent,\n    InputComponent,\n    CustomCompComponent,\n    NavbarComponent,\n    MatButtonToggleModule\n  ],\n  imports: [\n    MatSliderModule,\n    MatButtonToggleModule\n  ],\n  \n  \n})\nexport class UiComponentsModule {\n    constructor(){\n      console.log({\n        MatSliderModule\n      });\n      }\n\n\n }\n",
            "children": [
                {
                    "type": "providers",
                    "elements": []
                },
                {
                    "type": "declarations",
                    "elements": [
                        {
                            "name": "ButtonComponentComponent"
                        },
                        {
                            "name": "CustomCompComponent"
                        },
                        {
                            "name": "InputComponent"
                        },
                        {
                            "name": "NavbarComponent"
                        }
                    ]
                },
                {
                    "type": "imports",
                    "elements": []
                },
                {
                    "type": "exports",
                    "elements": [
                        {
                            "name": "ButtonComponentComponent"
                        },
                        {
                            "name": "CustomCompComponent"
                        },
                        {
                            "name": "InputComponent"
                        },
                        {
                            "name": "NavbarComponent"
                        }
                    ]
                },
                {
                    "type": "bootstrap",
                    "elements": []
                },
                {
                    "type": "classes",
                    "elements": []
                }
            ]
        }
    ],
    "miscellaneous": {
        "variables": [
            {
                "name": "bootstrap",
                "ctype": "miscellaneous",
                "subtype": "variable",
                "file": "src/main.single-spa.ts",
                "deprecated": false,
                "deprecationMessage": "",
                "type": "",
                "defaultValue": "lifecycles.bootstrap"
            },
            {
                "name": "context",
                "ctype": "miscellaneous",
                "subtype": "variable",
                "file": "src/test.ts",
                "deprecated": false,
                "deprecationMessage": "",
                "type": "",
                "defaultValue": "require.context('./', true, /\\.spec\\.ts$/)"
            },
            {
                "name": "context",
                "ctype": "miscellaneous",
                "subtype": "variable",
                "file": "projects/component-lib/src/test.ts",
                "deprecated": false,
                "deprecationMessage": "",
                "type": "",
                "defaultValue": "require.context('./', true, /\\.spec\\.ts$/)"
            },
            {
                "name": "Default",
                "ctype": "miscellaneous",
                "subtype": "variable",
                "file": "projects/component-lib/src/lib/stories/components/button-component/my-lib.stories.ts",
                "deprecated": false,
                "deprecationMessage": "",
                "type": "",
                "defaultValue": "Template.bind({})"
            },
            {
                "name": "Default",
                "ctype": "miscellaneous",
                "subtype": "variable",
                "file": "projects/component-lib/src/lib/stories/components/custom-comp/custom-comp.stories.ts",
                "deprecated": false,
                "deprecationMessage": "",
                "type": "",
                "defaultValue": "Template.bind({})"
            },
            {
                "name": "Default",
                "ctype": "miscellaneous",
                "subtype": "variable",
                "file": "projects/component-lib/src/lib/stories/components/input/input.stories.ts",
                "deprecated": false,
                "deprecationMessage": "",
                "type": "",
                "defaultValue": "Template.bind({})"
            },
            {
                "name": "Default",
                "ctype": "miscellaneous",
                "subtype": "variable",
                "file": "projects/component-lib/src/lib/stories/components/navbar/navbar.stories.ts",
                "deprecated": false,
                "deprecationMessage": "",
                "type": "",
                "defaultValue": "Template.bind({})"
            },
            {
                "name": "environment",
                "ctype": "miscellaneous",
                "subtype": "variable",
                "file": "src/environments/environment.prod.ts",
                "deprecated": false,
                "deprecationMessage": "",
                "type": "object",
                "defaultValue": "{\n  production: true\n}"
            },
            {
                "name": "environment",
                "ctype": "miscellaneous",
                "subtype": "variable",
                "file": "src/environments/environment.ts",
                "deprecated": false,
                "deprecationMessage": "",
                "type": "object",
                "defaultValue": "{\n  production: false\n}"
            },
            {
                "name": "lifecycles",
                "ctype": "miscellaneous",
                "subtype": "variable",
                "file": "src/main.single-spa.ts",
                "deprecated": false,
                "deprecationMessage": "",
                "type": "",
                "defaultValue": "singleSpaAngular({\n  bootstrapFunction: singleSpaProps => {\n    singleSpaPropsSubject.next(singleSpaProps);\n    return platformBrowserDynamic().bootstrapModule(AppModule);\n  },\n  template: '<comp-lib />',\n  NgZone,\n})"
            },
            {
                "name": "mount",
                "ctype": "miscellaneous",
                "subtype": "variable",
                "file": "src/main.single-spa.ts",
                "deprecated": false,
                "deprecationMessage": "",
                "type": "",
                "defaultValue": "lifecycles.mount"
            },
            {
                "name": "require",
                "ctype": "miscellaneous",
                "subtype": "variable",
                "file": "src/test.ts",
                "deprecated": false,
                "deprecationMessage": "",
                "type": "literal type"
            },
            {
                "name": "require",
                "ctype": "miscellaneous",
                "subtype": "variable",
                "file": "projects/component-lib/src/test.ts",
                "deprecated": false,
                "deprecationMessage": "",
                "type": "literal type"
            },
            {
                "name": "singleSpaPropsSubject",
                "ctype": "miscellaneous",
                "subtype": "variable",
                "file": "src/single-spa/single-spa-props.ts",
                "deprecated": false,
                "deprecationMessage": "",
                "type": "",
                "defaultValue": "new ReplaySubject<SingleSpaProps>(1)"
            },
            {
                "name": "Template",
                "ctype": "miscellaneous",
                "subtype": "variable",
                "file": "projects/component-lib/src/lib/stories/components/button-component/my-lib.stories.ts",
                "deprecated": false,
                "deprecationMessage": "",
                "type": "Story<ButtonComponentComponent>",
                "defaultValue": "(args: ButtonComponentComponent) => ({\n  props: args,\n})"
            },
            {
                "name": "Template",
                "ctype": "miscellaneous",
                "subtype": "variable",
                "file": "projects/component-lib/src/lib/stories/components/custom-comp/custom-comp.stories.ts",
                "deprecated": false,
                "deprecationMessage": "",
                "type": "Story<CustomCompComponent>",
                "defaultValue": "(args: CustomCompComponent) => ({\n  props: args,\n})"
            },
            {
                "name": "Template",
                "ctype": "miscellaneous",
                "subtype": "variable",
                "file": "projects/component-lib/src/lib/stories/components/input/input.stories.ts",
                "deprecated": false,
                "deprecationMessage": "",
                "type": "Story<InputComponent>",
                "defaultValue": "(args: InputComponent) => ({\n  props: args,\n})"
            },
            {
                "name": "Template",
                "ctype": "miscellaneous",
                "subtype": "variable",
                "file": "projects/component-lib/src/lib/stories/components/navbar/navbar.stories.ts",
                "deprecated": false,
                "deprecationMessage": "",
                "type": "Story<NavbarComponent>",
                "defaultValue": "(args: NavbarComponent) => ({\n  props: args,\n})"
            },
            {
                "name": "unmount",
                "ctype": "miscellaneous",
                "subtype": "variable",
                "file": "src/main.single-spa.ts",
                "deprecated": false,
                "deprecationMessage": "",
                "type": "",
                "defaultValue": "lifecycles.unmount"
            }
        ],
        "functions": [
            {
                "name": "assetUrl",
                "file": "src/single-spa/asset-url.ts",
                "ctype": "miscellaneous",
                "subtype": "function",
                "deprecated": false,
                "deprecationMessage": "",
                "description": "",
                "args": [
                    {
                        "name": "url",
                        "type": "string",
                        "deprecated": false,
                        "deprecationMessage": ""
                    }
                ],
                "returnType": "string",
                "jsdoctags": [
                    {
                        "name": "url",
                        "type": "string",
                        "deprecated": false,
                        "deprecationMessage": "",
                        "tagName": {
                            "text": "param"
                        }
                    }
                ]
            }
        ],
        "typealiases": [
            {
                "name": "SingleSpaProps",
                "ctype": "miscellaneous",
                "subtype": "typealias",
                "rawtype": "",
                "file": "src/single-spa/single-spa-props.ts",
                "deprecated": false,
                "deprecationMessage": "",
                "description": "",
                "kind": 187
            }
        ],
        "enumerations": [],
        "groupedVariables": {
            "src/main.single-spa.ts": [
                {
                    "name": "bootstrap",
                    "ctype": "miscellaneous",
                    "subtype": "variable",
                    "file": "src/main.single-spa.ts",
                    "deprecated": false,
                    "deprecationMessage": "",
                    "type": "",
                    "defaultValue": "lifecycles.bootstrap"
                },
                {
                    "name": "lifecycles",
                    "ctype": "miscellaneous",
                    "subtype": "variable",
                    "file": "src/main.single-spa.ts",
                    "deprecated": false,
                    "deprecationMessage": "",
                    "type": "",
                    "defaultValue": "singleSpaAngular({\n  bootstrapFunction: singleSpaProps => {\n    singleSpaPropsSubject.next(singleSpaProps);\n    return platformBrowserDynamic().bootstrapModule(AppModule);\n  },\n  template: '<comp-lib />',\n  NgZone,\n})"
                },
                {
                    "name": "mount",
                    "ctype": "miscellaneous",
                    "subtype": "variable",
                    "file": "src/main.single-spa.ts",
                    "deprecated": false,
                    "deprecationMessage": "",
                    "type": "",
                    "defaultValue": "lifecycles.mount"
                },
                {
                    "name": "unmount",
                    "ctype": "miscellaneous",
                    "subtype": "variable",
                    "file": "src/main.single-spa.ts",
                    "deprecated": false,
                    "deprecationMessage": "",
                    "type": "",
                    "defaultValue": "lifecycles.unmount"
                }
            ],
            "src/test.ts": [
                {
                    "name": "context",
                    "ctype": "miscellaneous",
                    "subtype": "variable",
                    "file": "src/test.ts",
                    "deprecated": false,
                    "deprecationMessage": "",
                    "type": "",
                    "defaultValue": "require.context('./', true, /\\.spec\\.ts$/)"
                },
                {
                    "name": "require",
                    "ctype": "miscellaneous",
                    "subtype": "variable",
                    "file": "src/test.ts",
                    "deprecated": false,
                    "deprecationMessage": "",
                    "type": "literal type"
                }
            ],
            "projects/component-lib/src/test.ts": [
                {
                    "name": "context",
                    "ctype": "miscellaneous",
                    "subtype": "variable",
                    "file": "projects/component-lib/src/test.ts",
                    "deprecated": false,
                    "deprecationMessage": "",
                    "type": "",
                    "defaultValue": "require.context('./', true, /\\.spec\\.ts$/)"
                },
                {
                    "name": "require",
                    "ctype": "miscellaneous",
                    "subtype": "variable",
                    "file": "projects/component-lib/src/test.ts",
                    "deprecated": false,
                    "deprecationMessage": "",
                    "type": "literal type"
                }
            ],
            "projects/component-lib/src/lib/stories/components/button-component/my-lib.stories.ts": [
                {
                    "name": "Default",
                    "ctype": "miscellaneous",
                    "subtype": "variable",
                    "file": "projects/component-lib/src/lib/stories/components/button-component/my-lib.stories.ts",
                    "deprecated": false,
                    "deprecationMessage": "",
                    "type": "",
                    "defaultValue": "Template.bind({})"
                },
                {
                    "name": "Template",
                    "ctype": "miscellaneous",
                    "subtype": "variable",
                    "file": "projects/component-lib/src/lib/stories/components/button-component/my-lib.stories.ts",
                    "deprecated": false,
                    "deprecationMessage": "",
                    "type": "Story<ButtonComponentComponent>",
                    "defaultValue": "(args: ButtonComponentComponent) => ({\n  props: args,\n})"
                }
            ],
            "projects/component-lib/src/lib/stories/components/custom-comp/custom-comp.stories.ts": [
                {
                    "name": "Default",
                    "ctype": "miscellaneous",
                    "subtype": "variable",
                    "file": "projects/component-lib/src/lib/stories/components/custom-comp/custom-comp.stories.ts",
                    "deprecated": false,
                    "deprecationMessage": "",
                    "type": "",
                    "defaultValue": "Template.bind({})"
                },
                {
                    "name": "Template",
                    "ctype": "miscellaneous",
                    "subtype": "variable",
                    "file": "projects/component-lib/src/lib/stories/components/custom-comp/custom-comp.stories.ts",
                    "deprecated": false,
                    "deprecationMessage": "",
                    "type": "Story<CustomCompComponent>",
                    "defaultValue": "(args: CustomCompComponent) => ({\n  props: args,\n})"
                }
            ],
            "projects/component-lib/src/lib/stories/components/input/input.stories.ts": [
                {
                    "name": "Default",
                    "ctype": "miscellaneous",
                    "subtype": "variable",
                    "file": "projects/component-lib/src/lib/stories/components/input/input.stories.ts",
                    "deprecated": false,
                    "deprecationMessage": "",
                    "type": "",
                    "defaultValue": "Template.bind({})"
                },
                {
                    "name": "Template",
                    "ctype": "miscellaneous",
                    "subtype": "variable",
                    "file": "projects/component-lib/src/lib/stories/components/input/input.stories.ts",
                    "deprecated": false,
                    "deprecationMessage": "",
                    "type": "Story<InputComponent>",
                    "defaultValue": "(args: InputComponent) => ({\n  props: args,\n})"
                }
            ],
            "projects/component-lib/src/lib/stories/components/navbar/navbar.stories.ts": [
                {
                    "name": "Default",
                    "ctype": "miscellaneous",
                    "subtype": "variable",
                    "file": "projects/component-lib/src/lib/stories/components/navbar/navbar.stories.ts",
                    "deprecated": false,
                    "deprecationMessage": "",
                    "type": "",
                    "defaultValue": "Template.bind({})"
                },
                {
                    "name": "Template",
                    "ctype": "miscellaneous",
                    "subtype": "variable",
                    "file": "projects/component-lib/src/lib/stories/components/navbar/navbar.stories.ts",
                    "deprecated": false,
                    "deprecationMessage": "",
                    "type": "Story<NavbarComponent>",
                    "defaultValue": "(args: NavbarComponent) => ({\n  props: args,\n})"
                }
            ],
            "src/environments/environment.prod.ts": [
                {
                    "name": "environment",
                    "ctype": "miscellaneous",
                    "subtype": "variable",
                    "file": "src/environments/environment.prod.ts",
                    "deprecated": false,
                    "deprecationMessage": "",
                    "type": "object",
                    "defaultValue": "{\n  production: true\n}"
                }
            ],
            "src/environments/environment.ts": [
                {
                    "name": "environment",
                    "ctype": "miscellaneous",
                    "subtype": "variable",
                    "file": "src/environments/environment.ts",
                    "deprecated": false,
                    "deprecationMessage": "",
                    "type": "object",
                    "defaultValue": "{\n  production: false\n}"
                }
            ],
            "src/single-spa/single-spa-props.ts": [
                {
                    "name": "singleSpaPropsSubject",
                    "ctype": "miscellaneous",
                    "subtype": "variable",
                    "file": "src/single-spa/single-spa-props.ts",
                    "deprecated": false,
                    "deprecationMessage": "",
                    "type": "",
                    "defaultValue": "new ReplaySubject<SingleSpaProps>(1)"
                }
            ]
        },
        "groupedFunctions": {
            "src/single-spa/asset-url.ts": [
                {
                    "name": "assetUrl",
                    "file": "src/single-spa/asset-url.ts",
                    "ctype": "miscellaneous",
                    "subtype": "function",
                    "deprecated": false,
                    "deprecationMessage": "",
                    "description": "",
                    "args": [
                        {
                            "name": "url",
                            "type": "string",
                            "deprecated": false,
                            "deprecationMessage": ""
                        }
                    ],
                    "returnType": "string",
                    "jsdoctags": [
                        {
                            "name": "url",
                            "type": "string",
                            "deprecated": false,
                            "deprecationMessage": "",
                            "tagName": {
                                "text": "param"
                            }
                        }
                    ]
                }
            ]
        },
        "groupedEnumerations": {},
        "groupedTypeAliases": {
            "src/single-spa/single-spa-props.ts": [
                {
                    "name": "SingleSpaProps",
                    "ctype": "miscellaneous",
                    "subtype": "typealias",
                    "rawtype": "",
                    "file": "src/single-spa/single-spa-props.ts",
                    "deprecated": false,
                    "deprecationMessage": "",
                    "description": "",
                    "kind": 187
                }
            ]
        }
    },
    "routes": [],
    "coverage": {
        "count": 0,
        "status": "low",
        "files": [
            {
                "filePath": "projects/component-lib/src/lib/stories/User.ts",
                "type": "interface",
                "linktype": "interface",
                "name": "User",
                "coveragePercent": 0,
                "coverageCount": "0/1",
                "status": "low"
            },
            {
                "filePath": "projects/component-lib/src/lib/stories/components/button-component/button-component.component.ts",
                "type": "component",
                "linktype": "component",
                "name": "ButtonComponentComponent",
                "coveragePercent": 0,
                "coverageCount": "0/4",
                "status": "low"
            },
            {
                "filePath": "projects/component-lib/src/lib/stories/components/button-component/my-lib.stories.ts",
                "type": "variable",
                "linktype": "miscellaneous",
                "linksubtype": "variable",
                "name": "Default",
                "coveragePercent": 0,
                "coverageCount": "0/1",
                "status": "low"
            },
            {
                "filePath": "projects/component-lib/src/lib/stories/components/button-component/my-lib.stories.ts",
                "type": "variable",
                "linktype": "miscellaneous",
                "linksubtype": "variable",
                "name": "Template",
                "coveragePercent": 0,
                "coverageCount": "0/1",
                "status": "low"
            },
            {
                "filePath": "projects/component-lib/src/lib/stories/components/custom-comp/custom-comp.component.ts",
                "type": "component",
                "linktype": "component",
                "name": "CustomCompComponent",
                "coveragePercent": 0,
                "coverageCount": "0/3",
                "status": "low"
            },
            {
                "filePath": "projects/component-lib/src/lib/stories/components/custom-comp/custom-comp.stories.ts",
                "type": "variable",
                "linktype": "miscellaneous",
                "linksubtype": "variable",
                "name": "Default",
                "coveragePercent": 0,
                "coverageCount": "0/1",
                "status": "low"
            },
            {
                "filePath": "projects/component-lib/src/lib/stories/components/custom-comp/custom-comp.stories.ts",
                "type": "variable",
                "linktype": "miscellaneous",
                "linksubtype": "variable",
                "name": "Template",
                "coveragePercent": 0,
                "coverageCount": "0/1",
                "status": "low"
            },
            {
                "filePath": "projects/component-lib/src/lib/stories/components/input/input.component.ts",
                "type": "component",
                "linktype": "component",
                "name": "InputComponent",
                "coveragePercent": 0,
                "coverageCount": "0/3",
                "status": "low"
            },
            {
                "filePath": "projects/component-lib/src/lib/stories/components/input/input.stories.ts",
                "type": "variable",
                "linktype": "miscellaneous",
                "linksubtype": "variable",
                "name": "Default",
                "coveragePercent": 0,
                "coverageCount": "0/1",
                "status": "low"
            },
            {
                "filePath": "projects/component-lib/src/lib/stories/components/input/input.stories.ts",
                "type": "variable",
                "linktype": "miscellaneous",
                "linksubtype": "variable",
                "name": "Template",
                "coveragePercent": 0,
                "coverageCount": "0/1",
                "status": "low"
            },
            {
                "filePath": "projects/component-lib/src/lib/stories/components/navbar/navbar.component.ts",
                "type": "component",
                "linktype": "component",
                "name": "NavbarComponent",
                "coveragePercent": 0,
                "coverageCount": "0/3",
                "status": "low"
            },
            {
                "filePath": "projects/component-lib/src/lib/stories/components/navbar/navbar.stories.ts",
                "type": "variable",
                "linktype": "miscellaneous",
                "linksubtype": "variable",
                "name": "Default",
                "coveragePercent": 0,
                "coverageCount": "0/1",
                "status": "low"
            },
            {
                "filePath": "projects/component-lib/src/lib/stories/components/navbar/navbar.stories.ts",
                "type": "variable",
                "linktype": "miscellaneous",
                "linksubtype": "variable",
                "name": "Template",
                "coveragePercent": 0,
                "coverageCount": "0/1",
                "status": "low"
            },
            {
                "filePath": "projects/component-lib/src/test.ts",
                "type": "variable",
                "linktype": "miscellaneous",
                "linksubtype": "variable",
                "name": "context",
                "coveragePercent": 0,
                "coverageCount": "0/1",
                "status": "low"
            },
            {
                "filePath": "projects/component-lib/src/test.ts",
                "type": "variable",
                "linktype": "miscellaneous",
                "linksubtype": "variable",
                "name": "require",
                "coveragePercent": 0,
                "coverageCount": "0/1",
                "status": "low"
            },
            {
                "filePath": "src/app/app.component.ts",
                "type": "component",
                "linktype": "component",
                "name": "AppComponent",
                "coveragePercent": 0,
                "coverageCount": "0/2",
                "status": "low"
            },
            {
                "filePath": "src/app/empty-route/empty-route.component.ts",
                "type": "component",
                "linktype": "component",
                "name": "EmptyRouteComponent",
                "coveragePercent": 0,
                "coverageCount": "0/1",
                "status": "low"
            },
            {
                "filePath": "src/environments/environment.prod.ts",
                "type": "variable",
                "linktype": "miscellaneous",
                "linksubtype": "variable",
                "name": "environment",
                "coveragePercent": 0,
                "coverageCount": "0/1",
                "status": "low"
            },
            {
                "filePath": "src/environments/environment.ts",
                "type": "variable",
                "linktype": "miscellaneous",
                "linksubtype": "variable",
                "name": "environment",
                "coveragePercent": 0,
                "coverageCount": "0/1",
                "status": "low"
            },
            {
                "filePath": "src/main.single-spa.ts",
                "type": "variable",
                "linktype": "miscellaneous",
                "linksubtype": "variable",
                "name": "bootstrap",
                "coveragePercent": 0,
                "coverageCount": "0/1",
                "status": "low"
            },
            {
                "filePath": "src/main.single-spa.ts",
                "type": "variable",
                "linktype": "miscellaneous",
                "linksubtype": "variable",
                "name": "lifecycles",
                "coveragePercent": 0,
                "coverageCount": "0/1",
                "status": "low"
            },
            {
                "filePath": "src/main.single-spa.ts",
                "type": "variable",
                "linktype": "miscellaneous",
                "linksubtype": "variable",
                "name": "mount",
                "coveragePercent": 0,
                "coverageCount": "0/1",
                "status": "low"
            },
            {
                "filePath": "src/main.single-spa.ts",
                "type": "variable",
                "linktype": "miscellaneous",
                "linksubtype": "variable",
                "name": "unmount",
                "coveragePercent": 0,
                "coverageCount": "0/1",
                "status": "low"
            },
            {
                "filePath": "src/single-spa/asset-url.ts",
                "type": "function",
                "linktype": "miscellaneous",
                "linksubtype": "function",
                "name": "assetUrl",
                "coveragePercent": 0,
                "coverageCount": "0/1",
                "status": "low"
            },
            {
                "filePath": "src/single-spa/single-spa-props.ts",
                "type": "variable",
                "linktype": "miscellaneous",
                "linksubtype": "variable",
                "name": "singleSpaPropsSubject",
                "coveragePercent": 0,
                "coverageCount": "0/1",
                "status": "low"
            },
            {
                "filePath": "src/test.ts",
                "type": "variable",
                "linktype": "miscellaneous",
                "linksubtype": "variable",
                "name": "context",
                "coveragePercent": 0,
                "coverageCount": "0/1",
                "status": "low"
            },
            {
                "filePath": "src/test.ts",
                "type": "variable",
                "linktype": "miscellaneous",
                "linksubtype": "variable",
                "name": "require",
                "coveragePercent": 0,
                "coverageCount": "0/1",
                "status": "low"
            }
        ]
    }
}